es2influx/__init__.py
es2influx/cli.py
es2influx/config.py
es2influx/transform.py
es2influx/utils.py
es2influx-0.1.0.dist-info/METADATA
es2influx-0.1.0.dist-info/WHEEL
es2influx-0.1.0.dist-info/entry_points.txt
es2influx-0.1.0.dist-info/RECORD
